{"sitedata":[{"sitename":"Fly My Community","icon":"/img/favicon.png","logo":"https://res.cloudinary.com/drjzrh756/image/upload/v1524244953/abifbzu7evsdptnaj0kf.png","metadesc":"Trusted By Fine Real Estate Professionals","metauthor":"Fly My Community","metakeyword":"cms"}],"content":[{"email":"bryan@pixvid.net","linkcont":"719-357-0329","videoid":"265856222","sliderbg":"/img/fly3_bg.jpg"}],"about":[{"abouttext1":"$50 a month!","abouttext2":"Gets you access to 30+ aerial community videos and the ability to create these lovely landing pages, for each and every individual client!","aboutbg":"/img/content_bg.png"}],"updatedDate":"2017-11-28T06:24:37.530Z"}